README.md
setup.py
F/EXT.py
F/__init__.py
F/CLASS/Callback.py
F/CLASS/Function.py
F/CLASS/Listener.py
F/CLASS/Process.py
F/CLASS/Promise.py
F/CLASS/Queue.py
F/CLASS/Routines.py
F/CLASS/Thread.py
F/CLASS/__init__.py
F/CONVERT/__init__.py
F/DATE/__init__.py
F/DICT/CountedDict.py
F/DICT/Generator.py
F/DICT/OrderedDict.py
F/DICT/__init__.py
F/FFMPEG/__init__.py
F/LIST/__init__.py
F/LOG/__init__.py
F/MATH/__init__.py
F/OS/__init__.py
F/RE/__init__.py
F/TYPE/Dict.py
F/TYPE/FDL.py
F/TYPE/List.py
F/TYPE/__init__.py
FairCore.egg-info/PKG-INFO
FairCore.egg-info/SOURCES.txt
FairCore.egg-info/dependency_links.txt
FairCore.egg-info/requires.txt
FairCore.egg-info/top_level.txt